tts_simple/__init__.py
tts_simple/core.py
tts_simple-0.1.2.dist-info/licenses/LICENSE
tts_simple-0.1.2.dist-info/METADATA
tts_simple-0.1.2.dist-info/WHEEL
tts_simple-0.1.2.dist-info/entry_points.txt
tts_simple-0.1.2.dist-info/top_level.txt
tts_simple-0.1.2.dist-info/RECORD
