Metadata-Version: 2.4
Name: tts-simple
Version: 0.1.2
Summary: Simple text-to-speech converter with multiple languages and voices
Home-page: https://github.com/HMCorp-Fund/tts_simple
Author: Anton Pavlenko
Author-email: apavlenko@hmcorp.fund
Classifier: Programming Language :: Python :: 3
Classifier: License :: OSI Approved :: MIT License
Classifier: Operating System :: OS Independent
Requires-Python: >=3.6
License-File: LICENSE
Requires-Dist: gTTS>=2.2.0
Dynamic: author
Dynamic: author-email
Dynamic: classifier
Dynamic: description
Dynamic: description-content-type
Dynamic: home-page
Dynamic: license-file
Dynamic: requires-dist
Dynamic: requires-python
Dynamic: summary
